{"example": ["She", "lent", "her", "friend", "a", "book", "."], "BIO": ["B-ARG0", "O", "B-ARG2", "I-ARG2", "B-ARG1", "I-ARG1", "O"], "allenBERT_pred": ["B-ARG0", "O", "B-ARG2", "I-ARG2", "B-ARG1", "I-ARG1", "O"], "allenBiLSTM_pred": ["B-ARG0", "O", "B-ARG2", "I-ARG2", "B-ARG1", "I-ARG1", "O"]}
{"example": ["He", "showed", "his", "wife", "a", "sunset", "."], "BIO": ["B-ARG0", "O", "B-ARG2", "I-ARG2", "B-ARG1", "I-ARG1", "O"], "allenBERT_pred": ["B-ARG0", "O", "B-ARG2", "I-ARG2", "B-ARG1", "I-ARG1", "O"], "allenBiLSTM_pred": ["B-ARG0", "O", "B-ARG2", "I-ARG2", "B-ARG1", "I-ARG1", "O"]}
{"example": ["She", "sent", "her", "mother", "a", "bouquet", "."], "BIO": ["B-ARG0", "O", "B-ARG2", "I-ARG2", "B-ARG1", "I-ARG1", "O"], "allenBERT_pred": ["B-ARG0", "O", "B-ARG2", "I-ARG2", "B-ARG1", "I-ARG1", "O"], "allenBiLSTM_pred": ["B-ARG0", "O", "B-ARG2", "I-ARG2", "B-ARG1", "I-ARG1", "O"]}
{"example": ["She", "cooked", "her", "grandmother", "a", "meal", "."], "BIO": ["B-ARG0", "O", "B-ARG2", "I-ARG2", "B-ARG1", "I-ARG1", "O"], "allenBERT_pred": ["B-ARG0", "O", "B-ARG3", "I-ARG3", "B-ARG1", "I-ARG1", "O"], "allenBiLSTM_pred": ["B-ARG0", "O", "B-ARG2", "I-ARG2", "B-ARG1", "I-ARG1", "O"]}
{"example": ["He", "gave", "his", "boss", "a", "gift", "."], "BIO": ["B-ARG0", "O", "B-ARG2", "I-ARG2", "B-ARG1", "I-ARG1", "O"], "allenBERT_pred": ["B-ARG0", "O", "B-ARG2", "I-ARG2", "B-ARG1", "I-ARG1", "O"], "allenBiLSTM_pred": ["B-ARG0", "O", "B-ARG2", "I-ARG2", "B-ARG1", "I-ARG1", "O"]}
{"example": ["I", "wrote", "my", "niece", "a", "letter", "."], "BIO": ["B-ARG0", "O", "B-ARG2", "I-ARG2", "B-ARG1", "I-ARG1", "O"], "allenBERT_pred": ["B-ARG0", "O", "B-ARG2", "I-ARG2", "B-ARG1", "I-ARG1", "O"], "allenBiLSTM_pred": ["B-ARG0", "O", "B-ARG2", "I-ARG2", "B-ARG1", "I-ARG1", "O"]}
{"example": ["John", "bought", "his", "girlfriend", "a", "necklace", "."], "BIO": ["B-ARG0", "O", "B-ARG2", "I-ARG2", "B-ARG1", "I-ARG1", "O"], "allenBERT_pred": ["B-ARG0", "O", "B-ARG4", "I-ARG4", "B-ARG1", "I-ARG1", "O"], "allenBiLSTM_pred": ["B-ARG0", "O", "B-ARG2", "I-ARG2", "B-ARG1", "I-ARG1", "O"]}
{"example": ["Mary", "emailed", "her", "boss", "a", "note", "."], "BIO": ["B-ARG0", "O", "B-ARG2", "I-ARG2", "B-ARG1", "I-ARG1", "O"], "allenBERT_pred": ["B-ARG0", "O", "B-ARG2", "I-ARG2", "B-ARG1", "I-ARG1", "O"], "allenBiLSTM_pred": ["B-ARG0", "O", "B-ARG1", "I-ARG1", "I-ARG1", "I-ARG1", "O"]}
{"example": ["They", "offered", "their", "guests", "a", "snack", "."], "BIO": ["B-ARG0", "O", "B-ARG2", "I-ARG2", "B-ARG1", "I-ARG1", "O"], "allenBERT_pred": ["B-ARG0", "O", "B-ARG3", "I-ARG3", "B-ARG1", "I-ARG1", "O"], "allenBiLSTM_pred": ["B-ARG0", "O", "B-ARG3", "I-ARG3", "B-ARG1", "I-ARG1", "O"]}
{"example": ["She", "gave", "her", "friend", "a", "hug", "."], "BIO": ["B-ARG0", "O", "B-ARG2", "I-ARG2", "B-ARG1", "I-ARG1", "O"], "allenBERT_pred": ["B-ARG0", "O", "B-ARG2", "I-ARG2", "B-ARG1", "I-ARG1", "O"], "allenBiLSTM_pred": ["B-ARG0", "O", "B-ARG2", "I-ARG2", "B-ARG1", "I-ARG1", "O"]}
{"example": ["She", "offered", "her", "friend", "a", "hug", "."], "BIO": ["B-ARG0", "O", "B-ARG2", "I-ARG2", "B-ARG1", "I-ARG1", "O"], "allenBERT_pred": ["B-ARG0", "O", "B-ARG3", "I-ARG3", "B-ARG1", "I-ARG1", "O"], "allenBiLSTM_pred": ["B-ARG0", "O", "B-ARG3", "I-ARG3", "B-ARG1", "I-ARG1", "O"]}
{"example": ["She", "bought", "her", "friend", "a", "beer", "."], "BIO": ["B-ARG0", "O", "B-ARG2", "I-ARG2", "B-ARG1", "I-ARG1", "O"], "allenBERT_pred": ["B-ARG0", "O", "B-ARG4", "I-ARG4", "B-ARG1", "I-ARG1", "O"], "allenBiLSTM_pred": ["B-ARG0", "O", "B-ARG4", "I-ARG4", "B-ARG1", "I-ARG1", "O"]}
{"example": ["She", "gave", "her", "friend", "a", "beer", "."], "BIO": ["B-ARG0", "O", "B-ARG2", "I-ARG2", "B-ARG1", "I-ARG1", "O"], "allenBERT_pred": ["B-ARG0", "O", "B-ARG2", "I-ARG2", "B-ARG1", "I-ARG1", "O"], "allenBiLSTM_pred": ["B-ARG0", "O", "B-ARG2", "I-ARG2", "B-ARG1", "I-ARG1", "O"]}
{"example": ["She", "poured", "her", "friend", "a", "beer", "."], "BIO": ["B-ARG0", "O", "B-ARG2", "I-ARG2", "B-ARG1", "I-ARG1", "O"], "allenBERT_pred": ["B-ARG0", "O", "B-ARG3", "I-ARG3", "B-ARG1", "I-ARG1", "O"], "allenBiLSTM_pred": ["B-ARG0", "O", "B-ARG2", "I-ARG2", "B-ARG1", "I-ARG1", "O"]}
{"example": ["She", "offered", "her", "friend", "a", "beer", "."], "BIO": ["B-ARG0", "O", "B-ARG2", "I-ARG2", "B-ARG1", "I-ARG1", "O"], "allenBERT_pred": ["B-ARG0", "O", "B-ARG3", "I-ARG3", "B-ARG1", "I-ARG1", "O"], "allenBiLSTM_pred": ["B-ARG0", "O", "B-ARG3", "I-ARG3", "B-ARG1", "I-ARG1", "O"]}
{"example": ["She", "gave", "her", "friend", "a", "spoon", "."], "BIO": ["B-ARG0", "O", "B-ARG2", "I-ARG2", "B-ARG1", "I-ARG1", "O"], "allenBERT_pred": ["B-ARG0", "O", "B-ARG2", "I-ARG2", "B-ARG1", "I-ARG1", "O"], "allenBiLSTM_pred": ["B-ARG0", "O", "B-ARG2", "I-ARG2", "B-ARG1", "I-ARG1", "O"]}
{"example": ["She", "handed", "her", "friend", "a", "spoon", "."], "BIO": ["B-ARG0", "O", "B-ARG2", "I-ARG2", "B-ARG1", "I-ARG1", "O"], "allenBERT_pred": ["B-ARG0", "O", "B-ARG2", "I-ARG2", "B-ARG1", "I-ARG1", "O"], "allenBiLSTM_pred": ["B-ARG0", "O", "B-ARG2", "I-ARG2", "B-ARG1", "I-ARG1", "O"]}
{"example": ["She", "offered", "her", "friend", "a", "spoon", "."], "BIO": ["B-ARG0", "O", "B-ARG2", "I-ARG2", "B-ARG1", "I-ARG1", "O"], "allenBERT_pred": ["B-ARG0", "O", "B-ARG3", "I-ARG3", "B-ARG1", "I-ARG1", "O"], "allenBiLSTM_pred": ["B-ARG0", "O", "B-ARG3", "I-ARG3", "B-ARG1", "I-ARG1", "O"]}
{"example": ["She", "bought", "her", "friend", "a", "spoon", "."], "BIO": ["B-ARG0", "O", "B-ARG2", "I-ARG2", "B-ARG1", "I-ARG1", "O"], "allenBERT_pred": ["B-ARG0", "O", "B-ARG4", "I-ARG4", "B-ARG1", "I-ARG1", "O"], "allenBiLSTM_pred": ["B-ARG0", "O", "B-ARG4", "I-ARG4", "B-ARG1", "I-ARG1", "O"]}
{"example": ["She", "bought", "her", "friend", "a", "drink", "."], "BIO": ["B-ARG0", "O", "B-ARG2", "I-ARG2", "B-ARG1", "I-ARG1", "O"], "allenBERT_pred": ["B-ARG0", "O", "B-ARG4", "I-ARG4", "B-ARG1", "I-ARG1", "O"], "allenBiLSTM_pred": ["B-ARG0", "O", "B-ARG4", "I-ARG4", "B-ARG1", "I-ARG1", "O"]}
{"example": ["She", "gave", "her", "friend", "a", "drink", "."], "BIO": ["B-ARG0", "O", "B-ARG2", "I-ARG2", "B-ARG1", "I-ARG1", "O"], "allenBERT_pred": ["B-ARG0", "O", "B-ARG2", "I-ARG2", "B-ARG1", "I-ARG1", "O"], "allenBiLSTM_pred": ["B-ARG0", "O", "B-ARG2", "I-ARG2", "B-ARG1", "I-ARG1", "O"]}
{"example": ["She", "poured", "her", "friend", "a", "drink", "."], "BIO": ["B-ARG0", "O", "B-ARG2", "I-ARG2", "B-ARG1", "I-ARG1", "O"], "allenBERT_pred": ["B-ARG0", "O", "B-ARG3", "I-ARG3", "B-ARG1", "I-ARG1", "O"], "allenBiLSTM_pred": ["B-ARG0", "O", "B-ARG2", "I-ARG2", "B-ARG1", "I-ARG1", "O"]}
{"example": ["She", "offered", "her", "friend", "a", "drink", "."], "BIO": ["B-ARG0", "O", "B-ARG2", "I-ARG2", "B-ARG1", "I-ARG1", "O"], "allenBERT_pred": ["B-ARG0", "O", "B-ARG3", "I-ARG3", "B-ARG1", "I-ARG1", "O"], "allenBiLSTM_pred": ["B-ARG0", "O", "B-ARG3", "I-ARG3", "B-ARG1", "I-ARG1", "O"]}
{"example": ["She", "ordered", "her", "friend", "a", "drink", "."], "BIO": ["B-ARG0", "O", "B-ARG2", "I-ARG2", "B-ARG1", "I-ARG1", "O"], "allenBERT_pred": ["B-ARG0", "O", "B-ARG1", "I-ARG1", "B-ARG2", "I-ARG2", "O"], "allenBiLSTM_pred": ["B-ARG0", "O", "B-ARG1", "I-ARG1", "B-ARG2", "I-ARG2", "O"]}
{"example": ["She", "gave", "her", "friend", "a", "gift", "."], "BIO": ["B-ARG0", "O", "B-ARG2", "I-ARG2", "B-ARG1", "I-ARG1", "O"], "allenBERT_pred": ["B-ARG0", "O", "B-ARG2", "I-ARG2", "B-ARG1", "I-ARG1", "O"], "allenBiLSTM_pred": ["B-ARG0", "O", "B-ARG2", "I-ARG2", "B-ARG1", "I-ARG1", "O"]}
{"example": ["She", "sent", "her", "friend", "a", "gift", "."], "BIO": ["B-ARG0", "O", "B-ARG2", "I-ARG2", "B-ARG1", "I-ARG1", "O"], "allenBERT_pred": ["B-ARG0", "O", "B-ARG2", "I-ARG2", "B-ARG1", "I-ARG1", "O"], "allenBiLSTM_pred": ["B-ARG0", "O", "B-ARG2", "I-ARG2", "B-ARG1", "I-ARG1", "O"]}
{"example": ["She", "left", "her", "friend", "a", "gift", "."], "BIO": ["B-ARG0", "O", "B-ARG2", "I-ARG2", "B-ARG1", "I-ARG1", "O"], "allenBERT_pred": ["B-ARG0", "O", "B-ARG2", "I-ARG2", "B-ARG1", "I-ARG1", "O"], "allenBiLSTM_pred": ["B-ARG0", "O", "B-ARG2", "I-ARG2", "B-ARG1", "I-ARG1", "O"]}
{"example": ["She", "handed", "her", "friend", "a", "gift", "."], "BIO": ["B-ARG0", "O", "B-ARG2", "I-ARG2", "B-ARG1", "I-ARG1", "O"], "allenBERT_pred": ["B-ARG0", "O", "B-ARG2", "I-ARG2", "B-ARG1", "I-ARG1", "O"], "allenBiLSTM_pred": ["B-ARG0", "O", "B-ARG2", "I-ARG2", "B-ARG1", "I-ARG1", "O"]}
{"example": ["He", "gave", "his", "wife", "a", "hug", "."], "BIO": ["B-ARG0", "O", "B-ARG2", "I-ARG2", "B-ARG1", "I-ARG1", "O"], "allenBERT_pred": ["B-ARG0", "O", "B-ARG2", "I-ARG2", "B-ARG1", "I-ARG1", "O"], "allenBiLSTM_pred": ["B-ARG0", "O", "B-ARG2", "I-ARG2", "B-ARG1", "I-ARG1", "O"]}
{"example": ["He", "offered", "his", "wife", "a", "hug", "."], "BIO": ["B-ARG0", "O", "B-ARG2", "I-ARG2", "B-ARG1", "I-ARG1", "O"], "allenBERT_pred": ["B-ARG0", "O", "B-ARG3", "I-ARG3", "B-ARG1", "I-ARG1", "O"], "allenBiLSTM_pred": ["B-ARG0", "O", "B-ARG3", "I-ARG3", "B-ARG1", "I-ARG1", "O"]}
{"example": ["He", "wished", "his", "wife", "a", "hug", "."], "BIO": ["B-ARG0", "O", "B-ARG2", "I-ARG2", "B-ARG1", "I-ARG1", "O"], "allenBERT_pred": ["B-ARG0", "O", "B-ARG2", "I-ARG2", "B-ARG1", "I-ARG1", "O"], "allenBiLSTM_pred": ["B-ARG0", "O", "B-ARG2", "I-ARG2", "B-ARG1", "I-ARG1", "O"]}
{"example": ["He", "sent", "his", "wife", "a", "hug", "."], "BIO": ["B-ARG0", "O", "B-ARG2", "I-ARG2", "B-ARG1", "I-ARG1", "O"], "allenBERT_pred": ["B-ARG0", "O", "B-ARG2", "I-ARG2", "B-ARG1", "I-ARG1", "O"], "allenBiLSTM_pred": ["B-ARG0", "O", "B-ARG2", "I-ARG2", "B-ARG2", "I-ARG2", "O"]}
{"example": ["He", "gave", "his", "wife", "a", "card", "."], "BIO": ["B-ARG0", "O", "B-ARG2", "I-ARG2", "B-ARG1", "I-ARG1", "O"], "allenBERT_pred": ["B-ARG0", "O", "B-ARG2", "I-ARG2", "B-ARG1", "I-ARG1", "O"], "allenBiLSTM_pred": ["B-ARG0", "O", "B-ARG2", "I-ARG2", "B-ARG1", "I-ARG1", "O"]}
{"example": ["He", "sent", "his", "wife", "a", "card", "."], "BIO": ["B-ARG0", "O", "B-ARG2", "I-ARG2", "B-ARG1", "I-ARG1", "O"], "allenBERT_pred": ["B-ARG0", "O", "B-ARG2", "I-ARG2", "B-ARG1", "I-ARG1", "O"], "allenBiLSTM_pred": ["B-ARG0", "O", "B-ARG2", "I-ARG2", "B-ARG1", "I-ARG1", "O"]}
{"example": ["He", "handed", "his", "wife", "a", "card", "."], "BIO": ["B-ARG0", "O", "B-ARG2", "I-ARG2", "B-ARG1", "I-ARG1", "O"], "allenBERT_pred": ["B-ARG0", "O", "B-ARG2", "I-ARG2", "B-ARG1", "I-ARG1", "O"], "allenBiLSTM_pred": ["B-ARG0", "O", "B-ARG2", "I-ARG2", "B-ARG1", "I-ARG1", "O"]}
{"example": ["He", "mailed", "his", "wife", "a", "card", "."], "BIO": ["B-ARG0", "O", "B-ARG2", "I-ARG2", "B-ARG1", "I-ARG1", "O"], "allenBERT_pred": ["B-ARG0", "O", "B-ARG2", "I-ARG2", "B-ARG1", "I-ARG1", "O"], "allenBiLSTM_pred": ["B-ARG0", "O", "B-ARG2", "I-ARG2", "B-ARG1", "I-ARG1", "O"]}
{"example": ["He", "handed", "his", "wife", "a", "receipt", "."], "BIO": ["B-ARG0", "O", "B-ARG2", "I-ARG2", "B-ARG1", "I-ARG1", "O"], "allenBERT_pred": ["B-ARG0", "O", "B-ARG2", "I-ARG2", "B-ARG1", "I-ARG1", "O"], "allenBiLSTM_pred": ["B-ARG0", "O", "B-ARG2", "I-ARG2", "B-ARG1", "I-ARG1", "O"]}
{"example": ["He", "gave", "his", "wife", "a", "receipt", "."], "BIO": ["B-ARG0", "O", "B-ARG2", "I-ARG2", "B-ARG1", "I-ARG1", "O"], "allenBERT_pred": ["B-ARG0", "O", "B-ARG2", "I-ARG2", "B-ARG1", "I-ARG1", "O"], "allenBiLSTM_pred": ["B-ARG0", "O", "B-ARG2", "I-ARG2", "B-ARG1", "I-ARG1", "O"]}
{"example": ["He", "sent", "his", "wife", "a", "receipt", "."], "BIO": ["B-ARG0", "O", "B-ARG2", "I-ARG2", "B-ARG1", "I-ARG1", "O"], "allenBERT_pred": ["B-ARG0", "O", "B-ARG2", "I-ARG2", "B-ARG1", "I-ARG1", "O"], "allenBiLSTM_pred": ["B-ARG0", "O", "B-ARG2", "I-ARG2", "B-ARG1", "I-ARG1", "O"]}
{"example": ["He", "mailed", "his", "wife", "a", "receipt", "."], "BIO": ["B-ARG0", "O", "B-ARG2", "I-ARG2", "B-ARG1", "I-ARG1", "O"], "allenBERT_pred": ["B-ARG0", "O", "B-ARG2", "I-ARG2", "B-ARG1", "I-ARG1", "O"], "allenBiLSTM_pred": ["B-ARG0", "O", "B-ARG2", "I-ARG2", "B-ARG1", "I-ARG1", "O"]}
{"example": ["He", "left", "his", "wife", "a", "receipt", "."], "BIO": ["B-ARG0", "O", "B-ARG2", "I-ARG2", "B-ARG1", "I-ARG1", "O"], "allenBERT_pred": ["B-ARG0", "O", "B-ARG2", "I-ARG2", "B-ARG1", "I-ARG1", "O"], "allenBiLSTM_pred": ["B-ARG0", "O", "B-ARG2", "I-ARG2", "B-ARG1", "I-ARG1", "O"]}
{"example": ["He", "gave", "his", "wife", "a", "medal", "."], "BIO": ["B-ARG0", "O", "B-ARG2", "I-ARG2", "B-ARG1", "I-ARG1", "O"], "allenBERT_pred": ["B-ARG0", "O", "B-ARG2", "I-ARG2", "B-ARG1", "I-ARG1", "O"], "allenBiLSTM_pred": ["B-ARG0", "O", "B-ARG2", "I-ARG2", "B-ARG1", "I-ARG1", "O"]}
{"example": ["He", "awarded", "his", "wife", "a", "medal", "."], "BIO": ["B-ARG0", "O", "B-ARG2", "I-ARG2", "B-ARG1", "I-ARG1", "O"], "allenBERT_pred": ["B-ARG0", "O", "B-ARG2", "I-ARG2", "B-ARG1", "I-ARG1", "O"], "allenBiLSTM_pred": ["B-ARG0", "O", "B-ARG2", "I-ARG2", "B-ARG1", "I-ARG1", "O"]}
{"example": ["He", "won", "his", "wife", "a", "medal", "."], "BIO": ["B-ARG0", "O", "B-ARG2", "I-ARG2", "B-ARG1", "I-ARG1", "O"], "allenBERT_pred": ["B-ARG0", "O", "B-ARG2", "I-ARG2", "B-ARG1", "I-ARG1", "O"], "allenBiLSTM_pred": ["B-ARG0", "O", "B-ARG2", "I-ARG2", "B-ARG1", "I-ARG1", "O"]}
{"example": ["He", "wished", "his", "wife", "a", "medal", "."], "BIO": ["B-ARG0", "O", "B-ARG2", "I-ARG2", "B-ARG1", "I-ARG1", "O"], "allenBERT_pred": ["B-ARG0", "O", "B-ARG2", "I-ARG2", "B-ARG1", "I-ARG1", "O"], "allenBiLSTM_pred": ["B-ARG0", "O", "B-ARG2", "I-ARG2", "B-ARG1", "I-ARG1", "O"]}
{"example": ["He", "earned", "his", "wife", "a", "medal", "."], "BIO": ["B-ARG0", "O", "B-ARG2", "I-ARG2", "B-ARG1", "I-ARG1", "O"], "allenBERT_pred": ["B-ARG0", "O", "B-ARG2", "I-ARG2", "B-ARG1", "I-ARG1", "O"], "allenBiLSTM_pred": ["B-ARG0", "O", "B-ARG2", "I-ARG2", "B-ARG1", "I-ARG1", "O"]}
{"example": ["He", "gave", "his", "wife", "a", "gift", "."], "BIO": ["B-ARG0", "O", "B-ARG2", "I-ARG2", "B-ARG1", "I-ARG1", "O"], "allenBERT_pred": ["B-ARG0", "O", "B-ARG2", "I-ARG2", "B-ARG1", "I-ARG1", "O"], "allenBiLSTM_pred": ["B-ARG0", "O", "B-ARG2", "I-ARG2", "B-ARG1", "I-ARG1", "O"]}
{"example": ["He", "sent", "his", "wife", "a", "gift", "."], "BIO": ["B-ARG0", "O", "B-ARG2", "I-ARG2", "B-ARG1", "I-ARG1", "O"], "allenBERT_pred": ["B-ARG0", "O", "B-ARG2", "I-ARG2", "B-ARG1", "I-ARG1", "O"], "allenBiLSTM_pred": ["B-ARG0", "O", "B-ARG2", "I-ARG2", "B-ARG1", "I-ARG1", "O"]}
{"example": ["He", "left", "his", "wife", "a", "gift", "."], "BIO": ["B-ARG0", "O", "B-ARG2", "I-ARG2", "B-ARG1", "I-ARG1", "O"], "allenBERT_pred": ["B-ARG0", "O", "B-ARG2", "I-ARG2", "B-ARG1", "I-ARG1", "O"], "allenBiLSTM_pred": ["B-ARG0", "O", "B-ARG2", "I-ARG2", "B-ARG1", "I-ARG1", "O"]}
{"example": ["He", "wished", "his", "wife", "a", "gift", "."], "BIO": ["B-ARG0", "O", "B-ARG2", "I-ARG2", "B-ARG1", "I-ARG1", "O"], "allenBERT_pred": ["B-ARG0", "O", "B-ARG2", "I-ARG2", "B-ARG1", "I-ARG1", "O"], "allenBiLSTM_pred": ["B-ARG0", "O", "B-ARG2", "I-ARG2", "B-ARG1", "I-ARG1", "O"]}
{"example": ["She", "wrote", "her", "mother", "a", "letter", "."], "BIO": ["B-ARG0", "O", "B-ARG2", "I-ARG2", "B-ARG1", "I-ARG1", "O"], "allenBERT_pred": ["B-ARG0", "O", "B-ARG2", "I-ARG2", "B-ARG1", "I-ARG1", "O"], "allenBiLSTM_pred": ["B-ARG0", "O", "B-ARG2", "I-ARG2", "B-ARG1", "I-ARG1", "O"]}
{"example": ["She", "sent", "her", "mother", "a", "letter", "."], "BIO": ["B-ARG0", "O", "B-ARG2", "I-ARG2", "B-ARG1", "I-ARG1", "O"], "allenBERT_pred": ["B-ARG0", "O", "B-ARG2", "I-ARG2", "B-ARG1", "I-ARG1", "O"], "allenBiLSTM_pred": ["B-ARG0", "O", "B-ARG2", "I-ARG2", "B-ARG1", "I-ARG1", "O"]}
{"example": ["She", "mailed", "her", "mother", "a", "letter", "."], "BIO": ["B-ARG0", "O", "B-ARG2", "I-ARG2", "B-ARG1", "I-ARG1", "O"], "allenBERT_pred": ["B-ARG0", "O", "B-ARG2", "I-ARG2", "B-ARG1", "I-ARG1", "O"], "allenBiLSTM_pred": ["B-ARG0", "O", "B-ARG2", "I-ARG2", "B-ARG1", "I-ARG1", "O"]}
{"example": ["She", "left", "her", "mother", "a", "letter", "."], "BIO": ["B-ARG0", "O", "B-ARG2", "I-ARG2", "B-ARG1", "I-ARG1", "O"], "allenBERT_pred": ["B-ARG0", "O", "B-ARG2", "I-ARG2", "B-ARG1", "I-ARG1", "O"], "allenBiLSTM_pred": ["B-ARG0", "O", "B-ARG2", "I-ARG2", "B-ARG1", "I-ARG1", "O"]}
{"example": ["She", "sent", "her", "mother", "a", "message", "."], "BIO": ["B-ARG0", "O", "B-ARG2", "I-ARG2", "B-ARG1", "I-ARG1", "O"], "allenBERT_pred": ["B-ARG0", "O", "B-ARG2", "I-ARG2", "B-ARG1", "I-ARG1", "O"], "allenBiLSTM_pred": ["B-ARG0", "O", "B-ARG2", "I-ARG2", "B-ARG1", "I-ARG1", "O"]}
{"example": ["She", "left", "her", "mother", "a", "message", "."], "BIO": ["B-ARG0", "O", "B-ARG2", "I-ARG2", "B-ARG1", "I-ARG1", "O"], "allenBERT_pred": ["B-ARG0", "O", "B-ARG2", "I-ARG2", "B-ARG1", "I-ARG1", "O"], "allenBiLSTM_pred": ["B-ARG0", "O", "B-ARG2", "I-ARG2", "B-ARG1", "I-ARG1", "O"]}
{"example": ["She", "wrote", "her", "mother", "a", "message", "."], "BIO": ["B-ARG0", "O", "B-ARG2", "I-ARG2", "B-ARG1", "I-ARG1", "O"], "allenBERT_pred": ["B-ARG0", "O", "B-ARG2", "I-ARG2", "B-ARG1", "I-ARG1", "O"], "allenBiLSTM_pred": ["B-ARG0", "O", "B-ARG2", "I-ARG2", "B-ARG1", "I-ARG1", "O"]}
{"example": ["She", "texted", "her", "mother", "a", "message", "."], "BIO": ["B-ARG0", "O", "B-ARG2", "I-ARG2", "B-ARG1", "I-ARG1", "O"], "allenBERT_pred": ["B-ARG0", "O", "B-ARG2", "I-ARG2", "B-ARG1", "I-ARG1", "O"], "allenBiLSTM_pred": ["B-ARG0", "O", "B-ARG2", "I-ARG2", "B-ARG1", "I-ARG1", "O"]}
{"example": ["She", "wrote", "her", "mother", "a", "note", "."], "BIO": ["B-ARG0", "O", "B-ARG2", "I-ARG2", "B-ARG1", "I-ARG1", "O"], "allenBERT_pred": ["B-ARG0", "O", "B-ARG2", "I-ARG2", "B-ARG1", "I-ARG1", "O"], "allenBiLSTM_pred": ["B-ARG0", "O", "B-ARG2", "I-ARG2", "B-ARG1", "I-ARG1", "O"]}
{"example": ["She", "left", "her", "mother", "a", "note", "."], "BIO": ["B-ARG0", "O", "B-ARG2", "I-ARG2", "B-ARG1", "I-ARG1", "O"], "allenBERT_pred": ["B-ARG0", "O", "B-ARG2", "I-ARG2", "B-ARG1", "I-ARG1", "O"], "allenBiLSTM_pred": ["B-ARG0", "O", "B-ARG2", "I-ARG2", "B-ARG1", "I-ARG1", "O"]}
{"example": ["She", "sent", "her", "mother", "a", "note", "."], "BIO": ["B-ARG0", "O", "B-ARG2", "I-ARG2", "B-ARG1", "I-ARG1", "O"], "allenBERT_pred": ["B-ARG0", "O", "B-ARG2", "I-ARG2", "B-ARG1", "I-ARG1", "O"], "allenBiLSTM_pred": ["B-ARG0", "O", "B-ARG2", "I-ARG2", "B-ARG1", "I-ARG1", "O"]}
{"example": ["She", "handed", "her", "mother", "a", "note", "."], "BIO": ["B-ARG0", "O", "B-ARG2", "I-ARG2", "B-ARG1", "I-ARG1", "O"], "allenBERT_pred": ["B-ARG0", "O", "B-ARG2", "I-ARG2", "B-ARG1", "I-ARG1", "O"], "allenBiLSTM_pred": ["B-ARG0", "O", "B-ARG2", "I-ARG2", "B-ARG1", "I-ARG1", "O"]}
{"example": ["She", "handed", "her", "mother", "a", "card", "."], "BIO": ["B-ARG0", "O", "B-ARG2", "I-ARG2", "B-ARG1", "I-ARG1", "O"], "allenBERT_pred": ["B-ARG0", "O", "B-ARG2", "I-ARG2", "B-ARG1", "I-ARG1", "O"], "allenBiLSTM_pred": ["B-ARG0", "O", "B-ARG2", "I-ARG2", "B-ARG1", "I-ARG1", "O"]}
{"example": ["She", "wrote", "her", "mother", "a", "card", "."], "BIO": ["B-ARG0", "O", "B-ARG2", "I-ARG2", "B-ARG1", "I-ARG1", "O"], "allenBERT_pred": ["B-ARG0", "O", "B-ARG2", "I-ARG2", "B-ARG1", "I-ARG1", "O"], "allenBiLSTM_pred": ["B-ARG0", "O", "B-ARG2", "I-ARG2", "B-ARG1", "I-ARG1", "O"]}
{"example": ["She", "sent", "her", "mother", "a", "card", "."], "BIO": ["B-ARG0", "O", "B-ARG2", "I-ARG2", "B-ARG1", "I-ARG1", "O"], "allenBERT_pred": ["B-ARG0", "O", "B-ARG2", "I-ARG2", "B-ARG1", "I-ARG1", "O"], "allenBiLSTM_pred": ["B-ARG0", "O", "B-ARG2", "I-ARG2", "B-ARG1", "I-ARG1", "O"]}
{"example": ["She", "gave", "her", "mother", "a", "card", "."], "BIO": ["B-ARG0", "O", "B-ARG2", "I-ARG2", "B-ARG1", "I-ARG1", "O"], "allenBERT_pred": ["B-ARG0", "O", "B-ARG2", "I-ARG2", "B-ARG1", "I-ARG1", "O"], "allenBiLSTM_pred": ["B-ARG0", "O", "B-ARG2", "I-ARG2", "B-ARG1", "I-ARG1", "O"]}
{"example": ["She", "mailed", "her", "mother", "a", "card", "."], "BIO": ["B-ARG0", "O", "B-ARG2", "I-ARG2", "B-ARG1", "I-ARG1", "O"], "allenBERT_pred": ["B-ARG0", "O", "B-ARG2", "I-ARG2", "B-ARG1", "I-ARG1", "O"], "allenBiLSTM_pred": ["B-ARG0", "O", "B-ARG2", "I-ARG2", "B-ARG1", "I-ARG1", "O"]}
{"example": ["She", "gave", "her", "mother", "a", "hug", "."], "BIO": ["B-ARG0", "O", "B-ARG2", "I-ARG2", "B-ARG1", "I-ARG1", "O"], "allenBERT_pred": ["B-ARG0", "O", "B-ARG2", "I-ARG2", "B-ARG1", "I-ARG1", "O"], "allenBiLSTM_pred": ["B-ARG0", "O", "B-ARG2", "I-ARG2", "B-ARG1", "I-ARG1", "O"]}
{"example": ["She", "offered", "her", "mother", "a", "hug", "."], "BIO": ["B-ARG0", "O", "B-ARG2", "I-ARG2", "B-ARG1", "I-ARG1", "O"], "allenBERT_pred": ["B-ARG0", "O", "B-ARG3", "I-ARG3", "B-ARG1", "I-ARG1", "O"], "allenBiLSTM_pred": ["B-ARG0", "O", "B-ARG3", "I-ARG3", "B-ARG1", "I-ARG1", "O"]}
{"example": ["She", "bought", "her", "grandmother", "a", "steak", "."], "BIO": ["B-ARG0", "O", "B-ARG2", "I-ARG2", "B-ARG1", "I-ARG1", "O"], "allenBERT_pred": ["B-ARG0", "O", "B-ARG4", "I-ARG4", "B-ARG1", "I-ARG1", "O"], "allenBiLSTM_pred": ["B-ARG0", "O", "B-ARG3", "I-ARG3", "B-ARG1", "I-ARG1", "O"]}
{"example": ["She", "cooked", "her", "grandmother", "a", "steak", "."], "BIO": ["B-ARG0", "O", "B-ARG2", "I-ARG2", "B-ARG1", "I-ARG1", "O"], "allenBERT_pred": ["B-ARG0", "O", "B-ARG3", "I-ARG3", "B-ARG1", "I-ARG1", "O"], "allenBiLSTM_pred": ["B-ARG0", "O", "B-ARG2", "I-ARG2", "B-ARG1", "I-ARG1", "O"]}
{"example": ["She", "gave", "her", "grandmother", "a", "steak", "."], "BIO": ["B-ARG0", "O", "B-ARG2", "I-ARG2", "B-ARG1", "I-ARG1", "O"], "allenBERT_pred": ["B-ARG0", "O", "B-ARG2", "I-ARG2", "B-ARG1", "I-ARG1", "O"], "allenBiLSTM_pred": ["B-ARG0", "O", "B-ARG2", "I-ARG2", "B-ARG1", "I-ARG1", "O"]}
{"example": ["She", "served", "her", "grandmother", "a", "steak", "."], "BIO": ["B-ARG0", "O", "B-ARG2", "I-ARG2", "B-ARG1", "I-ARG1", "O"], "allenBERT_pred": ["B-ARG0", "O", "B-ARG2", "I-ARG2", "B-ARG1", "I-ARG1", "O"], "allenBiLSTM_pred": ["B-ARG0", "O", "B-ARG2", "I-ARG2", "B-ARG1", "I-ARG1", "O"]}
{"example": ["She", "gave", "her", "grandmother", "a", "meal", "."], "BIO": ["B-ARG0", "O", "B-ARG2", "I-ARG2", "B-ARG1", "I-ARG1", "O"], "allenBERT_pred": ["B-ARG0", "O", "B-ARG2", "I-ARG2", "B-ARG1", "I-ARG1", "O"], "allenBiLSTM_pred": ["B-ARG0", "O", "B-ARG2", "I-ARG2", "B-ARG1", "I-ARG1", "O"]}
{"example": ["She", "bought", "her", "grandmother", "a", "meal", "."], "BIO": ["B-ARG0", "O", "B-ARG2", "I-ARG2", "B-ARG1", "I-ARG1", "O"], "allenBERT_pred": ["B-ARG0", "O", "B-ARG4", "I-ARG4", "B-ARG1", "I-ARG1", "O"], "allenBiLSTM_pred": ["B-ARG0", "O", "B-ARG4", "I-ARG4", "B-ARG1", "I-ARG1", "O"]}
{"example": ["She", "served", "her", "grandmother", "a", "meal", "."], "BIO": ["B-ARG0", "O", "B-ARG2", "I-ARG2", "B-ARG1", "I-ARG1", "O"], "allenBERT_pred": ["B-ARG0", "O", "B-ARG2", "I-ARG2", "B-ARG1", "I-ARG1", "O"], "allenBiLSTM_pred": ["B-ARG0", "O", "B-ARG2", "I-ARG2", "B-ARG1", "I-ARG1", "O"]}
{"example": ["She", "offered", "her", "grandmother", "a", "meal", "."], "BIO": ["B-ARG0", "O", "B-ARG2", "I-ARG2", "B-ARG1", "I-ARG1", "O"], "allenBERT_pred": ["B-ARG0", "O", "B-ARG3", "I-ARG3", "B-ARG1", "I-ARG1", "O"], "allenBiLSTM_pred": ["B-ARG0", "O", "B-ARG3", "I-ARG3", "B-ARG1", "I-ARG1", "O"]}
{"example": ["She", "cooked", "her", "grandmother", "a", "stew", "."], "BIO": ["B-ARG0", "O", "B-ARG2", "I-ARG2", "B-ARG1", "I-ARG1", "O"], "allenBERT_pred": ["B-ARG0", "O", "B-ARG3", "I-ARG3", "B-ARG1", "I-ARG1", "O"], "allenBiLSTM_pred": ["B-ARG0", "O", "B-ARG2", "I-ARG2", "B-ARG1", "I-ARG1", "O"]}
{"example": ["She", "served", "her", "grandmother", "a", "stew", "."], "BIO": ["B-ARG0", "O", "B-ARG2", "I-ARG2", "B-ARG1", "I-ARG1", "O"], "allenBERT_pred": ["B-ARG0", "O", "B-ARG2", "I-ARG2", "B-ARG1", "I-ARG1", "O"], "allenBiLSTM_pred": ["B-ARG0", "O", "B-ARG2", "I-ARG2", "B-ARG1", "I-ARG1", "O"]}
{"example": ["She", "fed", "her", "grandmother", "a", "stew", "."], "BIO": ["B-ARG0", "O", "B-ARG2", "I-ARG2", "B-ARG1", "I-ARG1", "O"], "allenBERT_pred": ["B-ARG0", "O", "B-ARG2", "I-ARG2", "B-ARG1", "I-ARG1", "O"], "allenBiLSTM_pred": ["B-ARG0", "O", "B-ARG1", "I-ARG1", "B-ARG2", "I-ARG2", "O"]}
{"example": ["She", "bought", "her", "grandmother", "a", "stew", "."], "BIO": ["B-ARG0", "O", "B-ARG2", "I-ARG2", "B-ARG1", "I-ARG1", "O"], "allenBERT_pred": ["B-ARG0", "O", "B-ARG4", "I-ARG4", "B-ARG1", "I-ARG1", "O"], "allenBiLSTM_pred": ["B-ARG0", "O", "B-ARG4", "I-ARG4", "B-ARG1", "I-ARG1", "O"]}
{"example": ["She", "gave", "her", "grandmother", "a", "stew", "."], "BIO": ["B-ARG0", "O", "B-ARG2", "I-ARG2", "B-ARG1", "I-ARG1", "O"], "allenBERT_pred": ["B-ARG0", "O", "B-ARG2", "I-ARG2", "B-ARG1", "I-ARG1", "O"], "allenBiLSTM_pred": ["B-ARG0", "O", "B-ARG2", "I-ARG2", "B-ARG1", "I-ARG1", "O"]}
{"example": ["She", "bought", "her", "grandmother", "a", "sandwich", "."], "BIO": ["B-ARG0", "O", "B-ARG2", "I-ARG2", "B-ARG1", "I-ARG1", "O"], "allenBERT_pred": ["B-ARG0", "O", "B-ARG4", "I-ARG4", "B-ARG1", "I-ARG1", "O"], "allenBiLSTM_pred": ["B-ARG0", "O", "B-ARG3", "I-ARG3", "B-ARG1", "I-ARG1", "O"]}
{"example": ["She", "gave", "her", "grandmother", "a", "sandwich", "."], "BIO": ["B-ARG0", "O", "B-ARG2", "I-ARG2", "B-ARG1", "I-ARG1", "O"], "allenBERT_pred": ["B-ARG0", "O", "B-ARG2", "I-ARG2", "B-ARG1", "I-ARG1", "O"], "allenBiLSTM_pred": ["B-ARG0", "O", "B-ARG2", "I-ARG2", "B-ARG1", "I-ARG1", "O"]}
{"example": ["She", "sent", "her", "grandmother", "a", "sandwich", "."], "BIO": ["B-ARG0", "O", "B-ARG2", "I-ARG2", "B-ARG1", "I-ARG1", "O"], "allenBERT_pred": ["B-ARG0", "O", "B-ARG2", "I-ARG2", "B-ARG1", "I-ARG1", "O"], "allenBiLSTM_pred": ["B-ARG0", "O", "B-ARG2", "I-ARG2", "B-ARG1", "I-ARG1", "O"]}
{"example": ["She", "offered", "her", "grandmother", "a", "sandwich", "."], "BIO": ["B-ARG0", "O", "B-ARG2", "I-ARG2", "B-ARG1", "I-ARG1", "O"], "allenBERT_pred": ["B-ARG0", "O", "B-ARG3", "I-ARG3", "B-ARG1", "I-ARG1", "O"], "allenBiLSTM_pred": ["B-ARG0", "O", "B-ARG3", "I-ARG3", "B-ARG1", "I-ARG1", "O"]}
{"example": ["She", "left", "her", "grandmother", "a", "sandwich", "."], "BIO": ["B-ARG0", "O", "B-ARG2", "I-ARG2", "B-ARG1", "I-ARG1", "O"], "allenBERT_pred": ["B-ARG0", "O", "B-ARG2", "I-ARG2", "B-ARG1", "I-ARG1", "O"], "allenBiLSTM_pred": ["B-ARG0", "O", "B-ARG2", "I-ARG2", "B-ARG1", "I-ARG1", "O"]}
{"example": ["She", "bought", "her", "grandmother", "a", "pie", "."], "BIO": ["B-ARG0", "O", "B-ARG2", "I-ARG2", "B-ARG1", "I-ARG1", "O"], "allenBERT_pred": ["B-ARG0", "O", "B-ARG4", "I-ARG4", "B-ARG1", "I-ARG1", "O"], "allenBiLSTM_pred": ["B-ARG0", "O", "B-ARG3", "I-ARG3", "B-ARG1", "I-ARG1", "O"]}
{"example": ["She", "baked", "her", "grandmother", "a", "pie", "."], "BIO": ["B-ARG0", "O", "B-ARG2", "I-ARG2", "B-ARG1", "I-ARG1", "O"], "allenBERT_pred": ["B-ARG0", "O", "B-ARG4", "I-ARG4", "B-ARG1", "I-ARG1", "O"], "allenBiLSTM_pred": ["B-ARG0", "O", "B-ARG2", "I-ARG2", "B-ARG1", "I-ARG1", "O"]}
{"example": ["She", "gave", "her", "grandmother", "a", "pie", "."], "BIO": ["B-ARG0", "O", "B-ARG2", "I-ARG2", "B-ARG1", "I-ARG1", "O"], "allenBERT_pred": ["B-ARG0", "O", "B-ARG2", "I-ARG2", "B-ARG1", "I-ARG1", "O"], "allenBiLSTM_pred": ["B-ARG0", "O", "B-ARG2", "I-ARG2", "B-ARG1", "I-ARG1", "O"]}
{"example": ["She", "served", "her", "grandmother", "a", "pie", "."], "BIO": ["B-ARG0", "O", "B-ARG2", "I-ARG2", "B-ARG1", "I-ARG1", "O"], "allenBERT_pred": ["B-ARG0", "O", "B-ARG2", "I-ARG2", "B-ARG1", "I-ARG1", "O"], "allenBiLSTM_pred": ["B-ARG0", "O", "B-ARG2", "I-ARG2", "B-ARG1", "I-ARG1", "O"]}
{"example": ["She", "handed", "her", "grandmother", "a", "pie", "."], "BIO": ["B-ARG0", "O", "B-ARG2", "I-ARG2", "B-ARG1", "I-ARG1", "O"], "allenBERT_pred": ["B-ARG0", "O", "B-ARG2", "I-ARG2", "B-ARG1", "I-ARG1", "O"], "allenBiLSTM_pred": ["B-ARG0", "O", "B-ARG2", "I-ARG2", "B-ARG1", "I-ARG1", "O"]}
{"example": ["He", "gave", "his", "boss", "a", "hug", "."], "BIO": ["B-ARG0", "O", "B-ARG2", "I-ARG2", "B-ARG1", "I-ARG1", "O"], "allenBERT_pred": ["B-ARG0", "O", "B-ARG2", "I-ARG2", "B-ARG1", "I-ARG1", "O"], "allenBiLSTM_pred": ["B-ARG0", "O", "B-ARG2", "I-ARG2", "B-ARG1", "I-ARG1", "O"]}
{"example": ["He", "offered", "his", "boss", "a", "hug", "."], "BIO": ["B-ARG0", "O", "B-ARG2", "I-ARG2", "B-ARG1", "I-ARG1", "O"], "allenBERT_pred": ["B-ARG0", "O", "B-ARG3", "I-ARG3", "B-ARG1", "I-ARG1", "O"], "allenBiLSTM_pred": ["B-ARG0", "O", "B-ARG3", "I-ARG3", "B-ARG1", "I-ARG1", "O"]}
{"example": ["He", "threw", "his", "boss", "a", "hug", "."], "BIO": ["B-ARG0", "O", "B-ARG2", "I-ARG2", "B-ARG1", "I-ARG1", "O"], "allenBERT_pred": ["B-ARG0", "O", "B-ARG2", "I-ARG2", "B-ARG1", "I-ARG1", "O"], "allenBiLSTM_pred": ["B-ARG0", "O", "B-ARG1", "I-ARG1", "B-ARG2", "I-ARG2", "O"]}
{"example": ["He", "sent", "his", "boss", "a", "hug", "."], "BIO": ["B-ARG0", "O", "B-ARG2", "I-ARG2", "B-ARG1", "I-ARG1", "O"], "allenBERT_pred": ["B-ARG0", "O", "B-ARG2", "I-ARG2", "B-ARG1", "I-ARG1", "O"], "allenBiLSTM_pred": ["B-ARG0", "O", "B-ARG2", "I-ARG2", "B-ARG1", "I-ARG1", "O"]}
{"example": ["He", "gave", "his", "boss", "a", "pass", "."], "BIO": ["B-ARG0", "O", "B-ARG2", "I-ARG2", "B-ARG1", "I-ARG1", "O"], "allenBERT_pred": ["B-ARG0", "O", "B-ARG2", "I-ARG2", "B-ARG1", "I-ARG1", "O"], "allenBiLSTM_pred": ["B-ARG0", "O", "B-ARG2", "I-ARG2", "B-ARG1", "I-ARG1", "O"]}
{"example": ["He", "threw", "his", "boss", "a", "pass", "."], "BIO": ["B-ARG0", "O", "B-ARG2", "I-ARG2", "B-ARG1", "I-ARG1", "O"], "allenBERT_pred": ["B-ARG0", "O", "B-ARG2", "I-ARG2", "B-ARG1", "I-ARG1", "O"], "allenBiLSTM_pred": ["B-ARG0", "O", "B-ARG1", "I-ARG1", "B-ARG2", "I-ARG2", "O"]}
{"example": ["He", "handed", "his", "boss", "a", "pass", "."], "BIO": ["B-ARG0", "O", "B-ARG2", "I-ARG2", "B-ARG1", "I-ARG1", "O"], "allenBERT_pred": ["B-ARG0", "O", "B-ARG2", "I-ARG2", "B-ARG1", "I-ARG1", "O"], "allenBiLSTM_pred": ["B-ARG0", "O", "B-ARG2", "I-ARG2", "B-ARG2", "I-ARG2", "O"]}
{"example": ["He", "tossed", "his", "boss", "a", "pass", "."], "BIO": ["B-ARG0", "O", "B-ARG2", "I-ARG2", "B-ARG1", "I-ARG1", "O"], "allenBERT_pred": ["B-ARG0", "O", "B-ARG2", "I-ARG2", "B-ARG1", "I-ARG1", "O"], "allenBiLSTM_pred": ["B-ARG0", "O", "B-ARG1", "I-ARG1", "B-ARG2", "I-ARG2", "O"]}
{"example": ["He", "gave", "his", "boss", "a", "kiss", "."], "BIO": ["B-ARG0", "O", "B-ARG2", "I-ARG2", "B-ARG1", "I-ARG1", "O"], "allenBERT_pred": ["B-ARG0", "O", "B-ARG2", "I-ARG2", "B-ARG1", "I-ARG1", "O"], "allenBiLSTM_pred": ["B-ARG0", "O", "B-ARG2", "I-ARG2", "B-ARG1", "I-ARG1", "O"]}
{"example": ["He", "blew", "his", "boss", "a", "kiss", "."], "BIO": ["B-ARG0", "O", "B-ARG2", "I-ARG2", "B-ARG1", "I-ARG1", "O"], "allenBERT_pred": ["B-ARG0", "O", "B-ARG2", "I-ARG2", "B-ARG1", "I-ARG1", "O"], "allenBiLSTM_pred": ["B-ARG0", "O", "B-ARG1", "I-ARG1", "B-ARG2", "I-ARG2", "O"]}
{"example": ["He", "offered", "his", "boss", "a", "kiss", "."], "BIO": ["B-ARG0", "O", "B-ARG2", "I-ARG2", "B-ARG1", "I-ARG1", "O"], "allenBERT_pred": ["B-ARG0", "O", "B-ARG3", "I-ARG3", "B-ARG1", "I-ARG1", "O"], "allenBiLSTM_pred": ["B-ARG0", "O", "B-ARG3", "I-ARG3", "B-ARG1", "I-ARG1", "O"]}
{"example": ["He", "gave", "his", "boss", "a", "shove", "."], "BIO": ["B-ARG0", "O", "B-ARG2", "I-ARG2", "B-ARG1", "I-ARG1", "O"], "allenBERT_pred": ["B-ARG0", "O", "B-ARG2", "I-ARG2", "B-ARG1", "I-ARG1", "O"], "allenBiLSTM_pred": ["B-ARG0", "O", "B-ARG2", "I-ARG2", "B-ARG1", "I-ARG1", "O"]}
{"example": ["He", "threw", "his", "boss", "a", "shove", "."], "BIO": ["B-ARG0", "O", "B-ARG2", "I-ARG2", "B-ARG1", "I-ARG1", "O"], "allenBERT_pred": ["B-ARG0", "O", "B-ARG2", "I-ARG2", "B-ARG1", "I-ARG1", "O"], "allenBiLSTM_pred": ["B-ARG0", "O", "B-ARG1", "I-ARG1", "B-ARG2", "I-ARG2", "O"]}
{"example": ["He", "handed", "his", "boss", "a", "shove", "."], "BIO": ["B-ARG0", "O", "B-ARG2", "I-ARG2", "B-ARG1", "I-ARG1", "O"], "allenBERT_pred": ["B-ARG0", "O", "B-ARG2", "I-ARG2", "B-ARG1", "I-ARG1", "O"], "allenBiLSTM_pred": ["B-ARG0", "O", "B-ARG2", "I-ARG2", "B-ARG2", "I-ARG2", "O"]}
{"example": ["He", "gave", "his", "boss", "a", "lift", "."], "BIO": ["B-ARG0", "O", "B-ARG2", "I-ARG2", "B-ARG1", "I-ARG1", "O"], "allenBERT_pred": ["B-ARG0", "O", "B-ARG2", "I-ARG2", "B-ARG1", "I-ARG1", "O"], "allenBiLSTM_pred": ["B-ARG0", "O", "B-ARG2", "I-ARG2", "B-ARG1", "I-ARG1", "O"]}
{"example": ["He", "offered", "his", "boss", "a", "lift", "."], "BIO": ["B-ARG0", "O", "B-ARG2", "I-ARG2", "B-ARG1", "I-ARG1", "O"], "allenBERT_pred": ["B-ARG0", "O", "B-ARG3", "I-ARG3", "B-ARG1", "I-ARG1", "O"], "allenBiLSTM_pred": ["B-ARG0", "O", "B-ARG3", "I-ARG3", "B-ARG1", "I-ARG1", "O"]}
{"example": ["I", "sent", "my", "niece", "a", "letter", "."], "BIO": ["B-ARG0", "O", "B-ARG2", "I-ARG2", "B-ARG1", "I-ARG1", "O"], "allenBERT_pred": ["B-ARG0", "O", "B-ARG2", "I-ARG2", "B-ARG1", "I-ARG1", "O"], "allenBiLSTM_pred": ["B-ARG0", "O", "B-ARG2", "I-ARG2", "B-ARG1", "I-ARG1", "O"]}
{"example": ["I", "mailed", "my", "niece", "a", "letter", "."], "BIO": ["B-ARG0", "O", "B-ARG2", "I-ARG2", "B-ARG1", "I-ARG1", "O"], "allenBERT_pred": ["B-ARG0", "O", "B-ARG2", "I-ARG2", "B-ARG1", "I-ARG1", "O"], "allenBiLSTM_pred": ["B-ARG0", "O", "B-ARG2", "I-ARG2", "B-ARG1", "I-ARG1", "O"]}
{"example": ["I", "wrote", "my", "niece", "a", "poem", "."], "BIO": ["B-ARG0", "O", "B-ARG2", "I-ARG2", "B-ARG1", "I-ARG1", "O"], "allenBERT_pred": ["B-ARG0", "O", "B-ARG2", "I-ARG2", "B-ARG1", "I-ARG1", "O"], "allenBiLSTM_pred": ["B-ARG0", "O", "B-ARG2", "I-ARG2", "B-ARG1", "I-ARG1", "O"]}
{"example": ["I", "sent", "my", "niece", "a", "poem", "."], "BIO": ["B-ARG0", "O", "B-ARG2", "I-ARG2", "B-ARG1", "I-ARG1", "O"], "allenBERT_pred": ["B-ARG0", "O", "B-ARG2", "I-ARG2", "B-ARG1", "I-ARG1", "O"], "allenBiLSTM_pred": ["B-ARG0", "O", "B-ARG2", "I-ARG2", "B-ARG1", "I-ARG1", "O"]}
{"example": ["I", "read", "my", "niece", "a", "poem", "."], "BIO": ["B-ARG0", "O", "B-ARG2", "I-ARG2", "B-ARG1", "I-ARG1", "O"], "allenBERT_pred": ["B-ARG0", "O", "B-ARG1", "I-ARG1", "B-ARG1", "I-ARG1", "O"], "allenBiLSTM_pred": ["B-ARG0", "O", "B-ARG2", "I-ARG2", "B-ARG1", "I-ARG1", "O"]}
{"example": ["I", "sent", "my", "niece", "a", "note", "."], "BIO": ["B-ARG0", "O", "B-ARG2", "I-ARG2", "B-ARG1", "I-ARG1", "O"], "allenBERT_pred": ["B-ARG0", "O", "B-ARG2", "I-ARG2", "B-ARG1", "I-ARG1", "O"], "allenBiLSTM_pred": ["B-ARG0", "O", "B-ARG2", "I-ARG2", "B-ARG1", "I-ARG1", "O"]}
{"example": ["I", "wrote", "my", "niece", "a", "note", "."], "BIO": ["B-ARG0", "O", "B-ARG2", "I-ARG2", "B-ARG1", "I-ARG1", "O"], "allenBERT_pred": ["B-ARG0", "O", "B-ARG2", "I-ARG2", "B-ARG1", "I-ARG1", "O"], "allenBiLSTM_pred": ["B-ARG0", "O", "B-ARG2", "I-ARG2", "B-ARG1", "I-ARG1", "O"]}
{"example": ["I", "left", "my", "niece", "a", "note", "."], "BIO": ["B-ARG0", "O", "B-ARG2", "I-ARG2", "B-ARG1", "I-ARG1", "O"], "allenBERT_pred": ["B-ARG0", "O", "B-ARG2", "I-ARG2", "B-ARG1", "I-ARG1", "O"], "allenBiLSTM_pred": ["B-ARG0", "O", "B-ARG2", "I-ARG2", "B-ARG1", "I-ARG1", "O"]}
{"example": ["I", "wrote", "my", "niece", "a", "check", "."], "BIO": ["B-ARG0", "O", "B-ARG2", "I-ARG2", "B-ARG1", "I-ARG1", "O"], "allenBERT_pred": ["B-ARG0", "O", "B-ARG2", "I-ARG2", "B-ARG1", "I-ARG1", "O"], "allenBiLSTM_pred": ["B-ARG0", "O", "B-ARG2", "I-ARG2", "B-ARG1", "I-ARG1", "O"]}
{"example": ["I", "sent", "my", "niece", "a", "check", "."], "BIO": ["B-ARG0", "O", "B-ARG2", "I-ARG2", "B-ARG1", "I-ARG1", "O"], "allenBERT_pred": ["B-ARG0", "O", "B-ARG2", "I-ARG2", "B-ARG1", "I-ARG1", "O"], "allenBiLSTM_pred": ["B-ARG0", "O", "B-ARG2", "I-ARG2", "B-ARG1", "I-ARG1", "O"]}
{"example": ["I", "mailed", "my", "niece", "a", "check", "."], "BIO": ["B-ARG0", "O", "B-ARG2", "I-ARG2", "B-ARG1", "I-ARG1", "O"], "allenBERT_pred": ["B-ARG0", "O", "B-ARG2", "I-ARG2", "B-ARG1", "I-ARG1", "O"], "allenBiLSTM_pred": ["B-ARG0", "O", "B-ARG2", "I-ARG2", "B-ARG1", "I-ARG1", "O"]}
{"example": ["I", "sent", "my", "niece", "a", "message", "."], "BIO": ["B-ARG0", "O", "B-ARG2", "I-ARG2", "B-ARG1", "I-ARG1", "O"], "allenBERT_pred": ["B-ARG0", "O", "B-ARG2", "I-ARG2", "B-ARG1", "I-ARG1", "O"], "allenBiLSTM_pred": ["B-ARG0", "O", "B-ARG2", "I-ARG2", "B-ARG1", "I-ARG1", "O"]}
{"example": ["I", "left", "my", "niece", "a", "message", "."], "BIO": ["B-ARG0", "O", "B-ARG2", "I-ARG2", "B-ARG1", "I-ARG1", "O"], "allenBERT_pred": ["B-ARG0", "O", "B-ARG2", "I-ARG2", "B-ARG1", "I-ARG1", "O"], "allenBiLSTM_pred": ["B-ARG0", "O", "B-ARG2", "I-ARG2", "B-ARG1", "I-ARG1", "O"]}
{"example": ["I", "wrote", "my", "niece", "a", "message", "."], "BIO": ["B-ARG0", "O", "B-ARG2", "I-ARG2", "B-ARG1", "I-ARG1", "O"], "allenBERT_pred": ["B-ARG0", "O", "B-ARG2", "I-ARG2", "B-ARG1", "I-ARG1", "O"], "allenBiLSTM_pred": ["B-ARG0", "O", "B-ARG2", "I-ARG2", "B-ARG1", "I-ARG1", "O"]}
{"example": ["John", "bought", "his", "girlfriend", "a", "guitar", "."], "BIO": ["B-ARG0", "O", "B-ARG2", "I-ARG2", "B-ARG1", "I-ARG1", "O"], "allenBERT_pred": ["B-ARG0", "O", "B-ARG4", "I-ARG4", "B-ARG1", "I-ARG1", "O"], "allenBiLSTM_pred": ["B-ARG0", "O", "B-ARG3", "I-ARG3", "B-ARG1", "I-ARG1", "O"]}
{"example": ["John", "handed", "his", "girlfriend", "a", "guitar", "."], "BIO": ["B-ARG0", "O", "B-ARG2", "I-ARG2", "B-ARG1", "I-ARG1", "O"], "allenBERT_pred": ["B-ARG0", "O", "B-ARG2", "I-ARG2", "B-ARG1", "I-ARG1", "O"], "allenBiLSTM_pred": ["B-ARG0", "O", "B-ARG2", "I-ARG2", "B-ARG1", "I-ARG1", "O"]}
{"example": ["John", "gave", "his", "girlfriend", "a", "guitar", "."], "BIO": ["B-ARG0", "O", "B-ARG2", "I-ARG2", "B-ARG1", "I-ARG1", "O"], "allenBERT_pred": ["B-ARG0", "O", "B-ARG2", "I-ARG2", "B-ARG1", "I-ARG1", "O"], "allenBiLSTM_pred": ["B-ARG0", "O", "B-ARG2", "I-ARG2", "B-ARG1", "I-ARG1", "O"]}
{"example": ["John", "bought", "his", "girlfriend", "a", "Porsche", "."], "BIO": ["B-ARG0", "O", "B-ARG2", "I-ARG2", "B-ARG1", "I-ARG1", "O"], "allenBERT_pred": ["B-ARG0", "O", "B-ARG4", "I-ARG4", "B-ARG1", "I-ARG1", "O"], "allenBiLSTM_pred": ["B-ARG0", "O", "B-ARG1", "I-ARG1", "I-ARG1", "I-ARG1", "O"]}
{"example": ["John", "gifted", "his", "girlfriend", "a", "Porsche", "."], "BIO": ["B-ARG0", "O", "B-ARG2", "I-ARG2", "B-ARG1", "I-ARG1", "O"], "allenBERT_pred": ["B-ARG0", "O", "B-ARG2", "I-ARG2", "B-ARG1", "I-ARG1", "O"], "allenBiLSTM_pred": ["B-ARG0", "O", "B-ARG1", "I-ARG1", "B-ARG2", "I-ARG2", "O"]}
{"example": ["John", "gave", "his", "girlfriend", "a", "Porsche", "."], "BIO": ["B-ARG0", "O", "B-ARG2", "I-ARG2", "B-ARG1", "I-ARG1", "O"], "allenBERT_pred": ["B-ARG0", "O", "B-ARG2", "I-ARG2", "B-ARG1", "I-ARG1", "O"], "allenBiLSTM_pred": ["B-ARG0", "O", "B-ARG2", "I-ARG2", "B-ARG1", "I-ARG1", "O"]}
{"example": ["John", "bought", "his", "girlfriend", "a", "beer", "."], "BIO": ["B-ARG0", "O", "B-ARG2", "I-ARG2", "B-ARG1", "I-ARG1", "O"], "allenBERT_pred": ["B-ARG0", "O", "B-ARG4", "I-ARG4", "B-ARG1", "I-ARG1", "O"], "allenBiLSTM_pred": ["B-ARG0", "O", "B-ARG3", "I-ARG3", "B-ARG1", "I-ARG1", "O"]}
{"example": ["John", "gave", "his", "girlfriend", "a", "beer", "."], "BIO": ["B-ARG0", "O", "B-ARG2", "I-ARG2", "B-ARG1", "I-ARG1", "O"], "allenBERT_pred": ["B-ARG0", "O", "B-ARG2", "I-ARG2", "B-ARG1", "I-ARG1", "O"], "allenBiLSTM_pred": ["B-ARG0", "O", "B-ARG2", "I-ARG2", "B-ARG1", "I-ARG1", "O"]}
{"example": ["John", "offered", "his", "girlfriend", "a", "beer", "."], "BIO": ["B-ARG0", "O", "B-ARG2", "I-ARG2", "B-ARG1", "I-ARG1", "O"], "allenBERT_pred": ["B-ARG0", "O", "B-ARG3", "I-ARG3", "B-ARG1", "I-ARG1", "O"], "allenBiLSTM_pred": ["B-ARG0", "O", "B-ARG3", "I-ARG3", "B-ARG1", "I-ARG1", "O"]}
{"example": ["John", "handed", "his", "girlfriend", "a", "beer", "."], "BIO": ["B-ARG0", "O", "B-ARG2", "I-ARG2", "B-ARG1", "I-ARG1", "O"], "allenBERT_pred": ["B-ARG0", "O", "B-ARG2", "I-ARG2", "B-ARG1", "I-ARG1", "O"], "allenBiLSTM_pred": ["B-ARG0", "O", "B-ARG2", "I-ARG2", "B-ARG1", "I-ARG1", "O"]}
{"example": ["John", "bought", "his", "girlfriend", "a", "car", "."], "BIO": ["B-ARG0", "O", "B-ARG2", "I-ARG2", "B-ARG1", "I-ARG1", "O"], "allenBERT_pred": ["B-ARG0", "O", "B-ARG4", "I-ARG4", "B-ARG1", "I-ARG1", "O"], "allenBiLSTM_pred": ["B-ARG0", "O", "B-ARG4", "I-ARG4", "B-ARG1", "I-ARG1", "O"]}
{"example": ["John", "lent", "his", "girlfriend", "a", "car", "."], "BIO": ["B-ARG0", "O", "B-ARG2", "I-ARG2", "B-ARG1", "I-ARG1", "O"], "allenBERT_pred": ["B-ARG0", "O", "B-ARG2", "I-ARG2", "B-ARG1", "I-ARG1", "O"], "allenBiLSTM_pred": ["B-ARG0", "O", "B-ARG2", "I-ARG2", "B-ARG1", "I-ARG1", "O"]}
{"example": ["John", "gave", "his", "girlfriend", "a", "car", "."], "BIO": ["B-ARG0", "O", "B-ARG2", "I-ARG2", "B-ARG1", "I-ARG1", "O"], "allenBERT_pred": ["B-ARG0", "O", "B-ARG2", "I-ARG2", "B-ARG1", "I-ARG1", "O"], "allenBiLSTM_pred": ["B-ARG0", "O", "B-ARG2", "I-ARG2", "B-ARG1", "I-ARG1", "O"]}
{"example": ["John", "sold", "his", "girlfriend", "a", "car", "."], "BIO": ["B-ARG0", "O", "B-ARG2", "I-ARG2", "B-ARG1", "I-ARG1", "O"], "allenBERT_pred": ["B-ARG0", "O", "B-ARG2", "I-ARG2", "B-ARG1", "I-ARG1", "O"], "allenBiLSTM_pred": ["B-ARG0", "O", "B-ARG2", "I-ARG2", "B-ARG1", "I-ARG1", "O"]}
{"example": ["John", "bought", "his", "girlfriend", "a", "BMW", "."], "BIO": ["B-ARG0", "O", "B-ARG2", "I-ARG2", "B-ARG1", "I-ARG1", "O"], "allenBERT_pred": ["B-ARG0", "O", "B-ARG4", "I-ARG4", "B-ARG1", "I-ARG1", "O"], "allenBiLSTM_pred": ["B-ARG0", "O", "B-ARG2", "I-ARG2", "B-ARG1", "I-ARG1", "O"]}
{"example": ["John", "gave", "his", "girlfriend", "a", "BMW", "."], "BIO": ["B-ARG0", "O", "B-ARG2", "I-ARG2", "B-ARG1", "I-ARG1", "O"], "allenBERT_pred": ["B-ARG0", "O", "B-ARG2", "I-ARG2", "B-ARG1", "I-ARG1", "O"], "allenBiLSTM_pred": ["B-ARG0", "O", "B-ARG2", "I-ARG2", "B-ARG1", "I-ARG1", "O"]}
{"example": ["John", "lent", "his", "girlfriend", "a", "BMW", "."], "BIO": ["B-ARG0", "O", "B-ARG2", "I-ARG2", "B-ARG1", "I-ARG1", "O"], "allenBERT_pred": ["B-ARG0", "O", "B-ARG2", "I-ARG2", "B-ARG1", "I-ARG1", "O"], "allenBiLSTM_pred": ["B-ARG0", "O", "B-ARG2", "I-ARG2", "B-ARG1", "I-ARG1", "O"]}
{"example": ["Mary", "wrote", "her", "boss", "a", "letter", "."], "BIO": ["B-ARG0", "O", "B-ARG2", "I-ARG2", "B-ARG1", "I-ARG1", "O"], "allenBERT_pred": ["B-ARG0", "O", "B-ARG2", "I-ARG2", "B-ARG1", "I-ARG1", "O"], "allenBiLSTM_pred": ["B-ARG0", "O", "B-ARG2", "I-ARG2", "B-ARG1", "I-ARG1", "O"]}
{"example": ["Mary", "sent", "her", "boss", "a", "letter", "."], "BIO": ["B-ARG0", "O", "B-ARG2", "I-ARG2", "B-ARG1", "I-ARG1", "O"], "allenBERT_pred": ["B-ARG0", "O", "B-ARG2", "I-ARG2", "B-ARG1", "I-ARG1", "O"], "allenBiLSTM_pred": ["B-ARG0", "O", "B-ARG2", "I-ARG2", "B-ARG1", "I-ARG1", "O"]}
{"example": ["Mary", "mailed", "her", "boss", "a", "letter", "."], "BIO": ["B-ARG0", "O", "B-ARG2", "I-ARG2", "B-ARG1", "I-ARG1", "O"], "allenBERT_pred": ["B-ARG0", "O", "B-ARG2", "I-ARG2", "B-ARG1", "I-ARG1", "O"], "allenBiLSTM_pred": ["B-ARG0", "O", "B-ARG2", "I-ARG2", "B-ARG1", "I-ARG1", "O"]}
{"example": ["Mary", "sent", "her", "boss", "a", "statement", "."], "BIO": ["B-ARG0", "O", "B-ARG2", "I-ARG2", "B-ARG1", "I-ARG1", "O"], "allenBERT_pred": ["B-ARG0", "O", "B-ARG2", "I-ARG2", "B-ARG1", "I-ARG1", "O"], "allenBiLSTM_pred": ["B-ARG0", "O", "B-ARG2", "I-ARG2", "B-ARG1", "I-ARG1", "O"]}
{"example": ["Mary", "emailed", "her", "boss", "a", "statement", "."], "BIO": ["B-ARG0", "O", "B-ARG2", "I-ARG2", "B-ARG1", "I-ARG1", "O"], "allenBERT_pred": ["B-ARG0", "O", "B-ARG2", "I-ARG2", "B-ARG1", "I-ARG1", "O"], "allenBiLSTM_pred": ["B-ARG0", "O", "B-ARG1", "I-ARG1", "I-ARG1", "I-ARG1", "O"]}
{"example": ["Mary", "gave", "her", "boss", "a", "statement", "."], "BIO": ["B-ARG0", "O", "B-ARG2", "I-ARG2", "B-ARG1", "I-ARG1", "O"], "allenBERT_pred": ["B-ARG0", "O", "B-ARG2", "I-ARG2", "B-ARG1", "I-ARG1", "O"], "allenBiLSTM_pred": ["B-ARG0", "O", "B-ARG2", "I-ARG2", "B-ARG1", "I-ARG1", "O"]}
{"example": ["Mary", "issued", "her", "boss", "a", "statement", "."], "BIO": ["B-ARG0", "O", "B-ARG2", "I-ARG2", "B-ARG1", "I-ARG1", "O"], "allenBERT_pred": ["B-ARG0", "O", "B-ARG2", "I-ARG2", "B-ARG1", "I-ARG1", "O"], "allenBiLSTM_pred": ["B-ARG0", "O", "B-ARG2", "I-ARG2", "B-ARG1", "I-ARG1", "O"]}
{"example": ["Mary", "wrote", "her", "boss", "a", "statement", "."], "BIO": ["B-ARG0", "O", "B-ARG2", "I-ARG2", "B-ARG1", "I-ARG1", "O"], "allenBERT_pred": ["B-ARG0", "O", "B-ARG2", "I-ARG2", "B-ARG1", "I-ARG1", "O"], "allenBiLSTM_pred": ["B-ARG0", "O", "B-ARG2", "I-ARG2", "B-ARG1", "I-ARG1", "O"]}
{"example": ["Mary", "sent", "her", "boss", "a", "response", "."], "BIO": ["B-ARG0", "O", "B-ARG2", "I-ARG2", "B-ARG1", "I-ARG1", "O"], "allenBERT_pred": ["B-ARG0", "O", "B-ARG2", "I-ARG2", "B-ARG1", "I-ARG1", "O"], "allenBiLSTM_pred": ["B-ARG0", "O", "B-ARG1", "I-ARG1", "B-ARG2", "I-ARG2", "O"]}
{"example": ["Mary", "emailed", "her", "boss", "a", "response", "."], "BIO": ["B-ARG0", "O", "B-ARG2", "I-ARG2", "B-ARG1", "I-ARG1", "O"], "allenBERT_pred": ["B-ARG0", "O", "B-ARG2", "I-ARG2", "B-ARG1", "I-ARG1", "O"], "allenBiLSTM_pred": ["B-ARG0", "O", "B-ARG1", "I-ARG1", "B-ARG2", "I-ARG2", "O"]}
{"example": ["Mary", "gave", "her", "boss", "a", "response", "."], "BIO": ["B-ARG0", "O", "B-ARG2", "I-ARG2", "B-ARG1", "I-ARG1", "O"], "allenBERT_pred": ["B-ARG0", "O", "B-ARG2", "I-ARG2", "B-ARG1", "I-ARG1", "O"], "allenBiLSTM_pred": ["B-ARG0", "O", "B-ARG2", "I-ARG2", "B-ARG1", "I-ARG1", "O"]}
{"example": ["Mary", "texted", "her", "boss", "a", "response", "."], "BIO": ["B-ARG0", "O", "B-ARG2", "I-ARG2", "B-ARG1", "I-ARG1", "O"], "allenBERT_pred": ["B-ARG0", "O", "B-ARG2", "I-ARG2", "B-ARG1", "I-ARG1", "O"], "allenBiLSTM_pred": ["B-ARG0", "O", "B-ARG2", "I-ARG2", "B-ARG1", "I-ARG1", "O"]}
{"example": ["Mary", "wrote", "her", "boss", "a", "response", "."], "BIO": ["B-ARG0", "O", "B-ARG2", "I-ARG2", "B-ARG1", "I-ARG1", "O"], "allenBERT_pred": ["B-ARG0", "O", "B-ARG2", "I-ARG2", "B-ARG1", "I-ARG1", "O"], "allenBiLSTM_pred": ["B-ARG0", "O", "B-ARG2", "I-ARG2", "B-ARG1", "I-ARG1", "O"]}
{"example": ["Mary", "sent", "her", "boss", "a", "message", "."], "BIO": ["B-ARG0", "O", "B-ARG2", "I-ARG2", "B-ARG1", "I-ARG1", "O"], "allenBERT_pred": ["B-ARG0", "O", "B-ARG2", "I-ARG2", "B-ARG1", "I-ARG1", "O"], "allenBiLSTM_pred": ["B-ARG0", "O", "B-ARG2", "I-ARG2", "B-ARG2", "I-ARG2", "O"]}
{"example": ["Mary", "left", "her", "boss", "a", "message", "."], "BIO": ["B-ARG0", "O", "B-ARG2", "I-ARG2", "B-ARG1", "I-ARG1", "O"], "allenBERT_pred": ["B-ARG0", "O", "B-ARG2", "I-ARG2", "B-ARG1", "I-ARG1", "O"], "allenBiLSTM_pred": ["B-ARG0", "O", "B-ARG2", "I-ARG2", "B-ARG1", "I-ARG1", "O"]}
{"example": ["Mary", "wrote", "her", "boss", "a", "message", "."], "BIO": ["B-ARG0", "O", "B-ARG2", "I-ARG2", "B-ARG1", "I-ARG1", "O"], "allenBERT_pred": ["B-ARG0", "O", "B-ARG2", "I-ARG2", "B-ARG1", "I-ARG1", "O"], "allenBiLSTM_pred": ["B-ARG0", "O", "B-ARG2", "I-ARG2", "B-ARG1", "I-ARG1", "O"]}
{"example": ["Mary", "texted", "her", "boss", "a", "message", "."], "BIO": ["B-ARG0", "O", "B-ARG2", "I-ARG2", "B-ARG1", "I-ARG1", "O"], "allenBERT_pred": ["B-ARG0", "O", "B-ARG2", "I-ARG2", "B-ARG1", "I-ARG1", "O"], "allenBiLSTM_pred": ["B-ARG0", "O", "B-ARG2", "I-ARG2", "B-ARG1", "I-ARG1", "O"]}
{"example": ["Mary", "sent", "her", "boss", "a", "reply", "."], "BIO": ["B-ARG0", "O", "B-ARG2", "I-ARG2", "B-ARG1", "I-ARG1", "O"], "allenBERT_pred": ["B-ARG0", "O", "B-ARG2", "I-ARG2", "B-ARG1", "I-ARG1", "O"], "allenBiLSTM_pred": ["B-ARG0", "O", "B-ARG2", "I-ARG2", "B-ARG1", "I-ARG1", "O"]}
{"example": ["Mary", "emailed", "her", "boss", "a", "reply", "."], "BIO": ["B-ARG0", "O", "B-ARG2", "I-ARG2", "B-ARG1", "I-ARG1", "O"], "allenBERT_pred": ["B-ARG0", "O", "B-ARG2", "I-ARG2", "B-ARG1", "I-ARG1", "O"], "allenBiLSTM_pred": ["B-ARG0", "O", "B-ARG1", "I-ARG1", "O", "O", "O"]}
{"example": ["Mary", "gave", "her", "boss", "a", "reply", "."], "BIO": ["B-ARG0", "O", "B-ARG2", "I-ARG2", "B-ARG1", "I-ARG1", "O"], "allenBERT_pred": ["B-ARG0", "O", "B-ARG2", "I-ARG2", "B-ARG1", "I-ARG1", "O"], "allenBiLSTM_pred": ["B-ARG0", "O", "B-ARG2", "I-ARG2", "B-ARG1", "I-ARG1", "O"]}
{"example": ["Mary", "texted", "her", "boss", "a", "reply", "."], "BIO": ["B-ARG0", "O", "B-ARG2", "I-ARG2", "B-ARG1", "I-ARG1", "O"], "allenBERT_pred": ["B-ARG0", "O", "B-ARG2", "I-ARG2", "B-ARG1", "I-ARG1", "O"], "allenBiLSTM_pred": ["B-ARG0", "O", "B-ARG2", "I-ARG2", "B-ARG1", "I-ARG1", "O"]}
{"example": ["They", "offer", "their", "guests", "a", "meal", "."], "BIO": ["B-ARG0", "O", "B-ARG2", "I-ARG2", "B-ARG1", "I-ARG1", "O"], "allenBERT_pred": ["B-ARG0", "O", "B-ARG3", "I-ARG3", "B-ARG1", "I-ARG1", "O"], "allenBiLSTM_pred": ["B-ARG0", "O", "B-ARG1", "I-ARG1", "I-ARG1", "I-ARG1", "O"]}
{"example": ["They", "promised", "their", "guests", "a", "meal", "."], "BIO": ["B-ARG0", "O", "B-ARG2", "I-ARG2", "B-ARG1", "I-ARG1", "O"], "allenBERT_pred": ["B-ARG0", "O", "B-ARG1", "I-ARG1", "B-ARG2", "I-ARG2", "O"], "allenBiLSTM_pred": ["B-ARG0", "O", "B-ARG1", "I-ARG1", "B-ARG2", "I-ARG2", "O"]}
{"example": ["They", "offered", "their", "guests", "a", "meal", "."], "BIO": ["B-ARG0", "O", "B-ARG2", "I-ARG2", "B-ARG1", "I-ARG1", "O"], "allenBERT_pred": ["B-ARG0", "O", "B-ARG3", "I-ARG3", "B-ARG1", "I-ARG1", "O"], "allenBiLSTM_pred": ["B-ARG0", "O", "B-ARG3", "I-ARG3", "B-ARG1", "I-ARG1", "O"]}
{"example": ["They", "gave", "their", "guests", "a", "meal", "."], "BIO": ["B-ARG0", "O", "B-ARG2", "I-ARG2", "B-ARG1", "I-ARG1", "O"], "allenBERT_pred": ["B-ARG0", "O", "B-ARG2", "I-ARG2", "B-ARG1", "I-ARG1", "O"], "allenBiLSTM_pred": ["B-ARG0", "O", "B-ARG2", "I-ARG2", "B-ARG1", "I-ARG1", "O"]}
{"example": ["They", "gave", "their", "guests", "a", "drink", "."], "BIO": ["B-ARG0", "O", "B-ARG2", "I-ARG2", "B-ARG1", "I-ARG1", "O"], "allenBERT_pred": ["B-ARG0", "O", "B-ARG2", "I-ARG2", "B-ARG1", "I-ARG1", "O"], "allenBiLSTM_pred": ["B-ARG0", "O", "B-ARG2", "I-ARG2", "B-ARG1", "I-ARG1", "O"]}
{"example": ["They", "offered", "their", "guests", "a", "drink", "."], "BIO": ["B-ARG0", "O", "B-ARG2", "I-ARG2", "B-ARG1", "I-ARG1", "O"], "allenBERT_pred": ["B-ARG0", "O", "B-ARG3", "I-ARG3", "B-ARG1", "I-ARG1", "O"], "allenBiLSTM_pred": ["B-ARG0", "O", "B-ARG3", "I-ARG3", "B-ARG1", "I-ARG1", "O"]}
{"example": ["They", "bought", "their", "guests", "a", "drink", "."], "BIO": ["B-ARG0", "O", "B-ARG2", "I-ARG2", "B-ARG1", "I-ARG1", "O"], "allenBERT_pred": ["B-ARG0", "O", "B-ARG4", "I-ARG4", "B-ARG1", "I-ARG1", "O"], "allenBiLSTM_pred": ["B-ARG0", "O", "B-ARG1", "I-ARG1", "I-ARG1", "I-ARG1", "O"]}
{"example": ["They", "wished", "their", "guests", "a", "toast", "."], "BIO": ["B-ARG0", "O", "B-ARG2", "I-ARG2", "B-ARG1", "I-ARG1", "O"], "allenBERT_pred": ["B-ARG0", "O", "B-ARG2", "I-ARG2", "B-ARG1", "I-ARG1", "O"], "allenBiLSTM_pred": ["B-ARG0", "O", "B-ARG1", "I-ARG1", "I-ARG1", "I-ARG1", "O"]}
{"example": ["They", "gave", "their", "guests", "a", "toast", "."], "BIO": ["B-ARG0", "O", "B-ARG2", "I-ARG2", "B-ARG1", "I-ARG1", "O"], "allenBERT_pred": ["B-ARG0", "O", "B-ARG2", "I-ARG2", "B-ARG1", "I-ARG1", "O"], "allenBiLSTM_pred": ["B-ARG0", "O", "B-ARG2", "I-ARG2", "B-ARG1", "I-ARG1", "O"]}
{"example": ["They", "threw", "their", "guests", "a", "toast", "."], "BIO": ["B-ARG0", "O", "B-ARG2", "I-ARG2", "B-ARG1", "I-ARG1", "O"], "allenBERT_pred": ["B-ARG0", "O", "B-ARG2", "I-ARG2", "B-ARG1", "I-ARG1", "O"], "allenBiLSTM_pred": ["B-ARG0", "O", "B-ARG2", "I-ARG2", "B-ARG2", "I-ARG2", "O"]}
{"example": ["They", "offered", "their", "guests", "a", "toast", "."], "BIO": ["B-ARG0", "O", "B-ARG2", "I-ARG2", "B-ARG1", "I-ARG1", "O"], "allenBERT_pred": ["B-ARG0", "O", "B-ARG3", "I-ARG3", "B-ARG1", "I-ARG1", "O"], "allenBiLSTM_pred": ["B-ARG0", "O", "B-ARG3", "I-ARG3", "B-ARG1", "I-ARG1", "O"]}
{"example": ["They", "served", "their", "guests", "a", "cake", "."], "BIO": ["B-ARG0", "O", "B-ARG2", "I-ARG2", "B-ARG1", "I-ARG1", "O"], "allenBERT_pred": ["B-ARG0", "O", "B-ARG2", "I-ARG2", "B-ARG1", "I-ARG1", "O"], "allenBiLSTM_pred": ["B-ARG0", "O", "B-ARG2", "I-ARG2", "B-ARG1", "I-ARG1", "O"]}
{"example": ["They", "baked", "their", "guests", "a", "cake", "."], "BIO": ["B-ARG0", "O", "B-ARG2", "I-ARG2", "B-ARG1", "I-ARG1", "O"], "allenBERT_pred": ["B-ARG0", "O", "B-ARG3", "I-ARG3", "B-ARG1", "I-ARG1", "O"], "allenBiLSTM_pred": ["B-ARG0", "O", "B-ARG2", "I-ARG2", "B-ARG1", "I-ARG1", "O"]}
{"example": ["They", "bought", "their", "guests", "a", "cake", "."], "BIO": ["B-ARG0", "O", "B-ARG2", "I-ARG2", "B-ARG1", "I-ARG1", "O"], "allenBERT_pred": ["B-ARG0", "O", "B-ARG4", "I-ARG4", "B-ARG1", "I-ARG1", "O"], "allenBiLSTM_pred": ["B-ARG0", "O", "B-ARG1", "I-ARG1", "I-ARG1", "I-ARG1", "O"]}
{"example": ["They", "gave", "their", "guests", "a", "cake", "."], "BIO": ["B-ARG0", "O", "B-ARG2", "I-ARG2", "B-ARG1", "I-ARG1", "O"], "allenBERT_pred": ["B-ARG0", "O", "B-ARG2", "I-ARG2", "B-ARG1", "I-ARG1", "O"], "allenBiLSTM_pred": ["B-ARG0", "O", "B-ARG2", "I-ARG2", "B-ARG1", "I-ARG1", "O"]}
{"example": ["They", "gave", "their", "guests", "a", "hug", "."], "BIO": ["B-ARG0", "O", "B-ARG2", "I-ARG2", "B-ARG1", "I-ARG1", "O"], "allenBERT_pred": ["B-ARG0", "O", "B-ARG2", "I-ARG2", "B-ARG1", "I-ARG1", "O"], "allenBiLSTM_pred": ["B-ARG0", "O", "B-ARG2", "I-ARG2", "B-ARG1", "I-ARG1", "O"]}
{"example": ["They", "wished", "their", "guests", "a", "hug", "."], "BIO": ["B-ARG0", "O", "B-ARG2", "I-ARG2", "B-ARG1", "I-ARG1", "O"], "allenBERT_pred": ["B-ARG0", "O", "B-ARG2", "I-ARG2", "B-ARG1", "I-ARG1", "O"], "allenBiLSTM_pred": ["B-ARG0", "O", "B-ARG1", "I-ARG1", "I-ARG1", "I-ARG1", "O"]}
{"example": ["They", "offered", "their", "guests", "a", "hug", "."], "BIO": ["B-ARG0", "O", "B-ARG2", "I-ARG2", "B-ARG1", "I-ARG1", "O"], "allenBERT_pred": ["B-ARG0", "O", "B-ARG3", "I-ARG3", "B-ARG1", "I-ARG1", "O"], "allenBiLSTM_pred": ["B-ARG0", "O", "B-ARG3", "I-ARG3", "B-ARG1", "I-ARG1", "O"]}
